{
  "source_file": "input\\BV1ca411g7hK_【哲学与现实】全球资本主义的卡住_2022-09-13-04-37-36.txt",
  "analysis_history": [
    {
      "round": 1,
      "round_type": "基础分析",
      "result": "[QUESTION]\n\n世界秩序似乎分裂为两大对立阵营：一边是以技术和金融为主导的美欧，另一边是以能源和意识形态相抗衡的俄国与中东。这种划分的本质到底是什么？它们是真正互不相容的两种体系吗？而我们这些不属于任何一阵营的“第三世界”，又该如何看清自己的位置和处境？\n\n[THINK]\n\n这段分析的核心线索是全球资本主义体系被划分为两个功能不同的“极”：一个是以美欧为代表的、通过技术和金融霸权维持统治的“统治极”；另一个是以俄国和中东为代表的、通过能源和意识形态进行抵抗的“反抗极”。其内在矛盾在于，这两极看似对立，实则都属于同一个全球资本主义秩序，并不追求社会主义理想。这种结构性机制将世界划分为统治者、反抗者和被压迫者。证据体现在，美欧的统治力来源于“技术垄断、工业标准和金融霸权”，而俄国等的反抗则依赖于“低缘张力能源和意识形态拮抗”。而“我们”的位置被明确界定为体系内真正的“被压迫者”，是输出劳动力、转化成工业品的“第三世界宿舍”。这一分析的边界在于，它描述的是当前全球资本主义的内在矛盾，而非两种不同社会制度（如冷战时期）的外部冲突。\n\n[ANSWER]\n\n通常认为，当今世界的地缘冲突是不同文明或意识形态阵营的对决，但这可能忽略了冲突双方在根本制度上的一致性。这种看法往往将表面的对抗误读为体系的根本对立，从而看不清各方在同一个全球游戏中的真实角色。\n\n实际上，这种全球对峙并非两个不同体系的斗争，而是全球资本主义这一个体系内部的两种功能性角色的冲突。一方是居于统治地位的“统治极”，它依靠技术、金融和标准制定来维持其霸权；另一方则是利用能源、地缘等要素进行反抗的“反抗极”。尽管它们在具体利益和策略上相互拮抗，但双方都遵循着资本的逻辑，都属于这个全球资本主义秩序的玩家。在这个体系中，还存在着真正的被压迫者——那些输出廉价劳动力、将劳动力转化为工业品，甚至仅仅是出口原材料的广大第三世界。因此，我们的位置并非是在两极之间选边站队的支持者，而是在整个体系中被剥削的底层。我们与那两极的任何一方都不存在所谓的支持关系，因为从根本上讲，我们是这个体系真正的受害者。\n\n---\n\n[QUESTION]\n\n俄国与欧洲之间的冲突愈演愈烈，很多人将其比作一场新的冷战。但如果说这不是两大阵营的对抗，那这场冲突的本质究竟是什么？双方到底在争夺什么？为什么说这是一种“层级间”的、“不对称”的冲突？\n\n[THINK]\n\n此问题的核心线索是俄国与欧洲的冲突。其内在矛盾在于，这场冲突表面上是两个政治实体（俄国 vs 欧盟）的对决，但实质上是资本主义体系内部不同“层级”之间的矛盾转移。一方是“单个的大型民族国家”（俄国），另一方是“民族国家集群”（欧洲）。它们斗争的机制，是资本主义固有的“危机与投机的同步运动”在跨层级传导时卡住了。双方争夺的焦点是谁能占据“投机性”的位置，同时把“危机性”甩给对方。证据在于，冲突被描述为“资本主义的层级间冲突”，而非“两大阵营的冲突”，性质与冷战完全不同。双方都在争取“谁来占据投机性，谁来把危机性甩给对方”。这个分析的边界在于，它仅适用于解释资本主义体系内部的矛盾运动，而不适用于不同社会制度之间的根本性对抗。\n\n[ANSWER]\n\n将俄欧冲突简单地视为新冷战，实际上是套用了一个过时的框架。这种看法模糊了冲突的真实性质，因为它假定双方代表着两个根本对立的体系，而事实并非如此。\n\n这场冲突的本质并非阵营对抗，而是资本主义体系内部在不同组织层级之间的矛盾爆发。它是一场“单个大型民族国家”（俄国）与一个“民族国家集群”（欧洲）之间的不对称较量。资本主义的运行逻辑，就是不断地将内部产生的“危机”转移到其他地方，并将其转化为自身的“投机”机会。这场冲突，正是这种危机与投机在两个相邻层级之间传导时卡住了的表现。双方争夺的核心，就是谁能成功占据有利的“投机者”位置，把灾难性的“危机”成本强加给对方。欧洲想把危机甩给俄国，自己坐享投机之利；俄国则想反过来做。因此，这不是意识形态的战争，而是一场在资本主义规则下，围绕着危机与利益分配的、发生在不同结构层级之间的内部斗争。\n\n---\n\n[QUESTION]\n\n面对一个问题重重的体系，很多人认为应该“加速”，让它快点崩溃。但有一种截然相反的观点是，我们应该追求让这个体系“卡住”。让全球资本主义“卡住”究竟是什么意思？为什么说“卡住”比“加速”更好？这种“卡住”的状态又是如何实现的？\n\n[THINK]\n\n此问题的核心线索是“卡住”（好事多磨）与“加速主义”的对立。其内在矛盾在于，直觉上加速崩溃似乎是激进的解决方案，但实际上，“加速”恰恰顺应了资本主义本身追求极限速度的逻辑。真正的颠覆性策略是让其“卡住”。其运行机制在于，资本主义通过“危机”与“投机”的快速同步循环来转移矛盾、延续自身。所谓“卡住”，就是通过某种方式，使得危机无法再顺利地转化为投机，让这个循环失败，时间性的链条被诊断。证据在于，资本主义的时间性本身就是“追求极限的快速加速”，而“加速主义”被视为一种“盲动的恐怖主义”。实现“卡住”的关键是“使得资本主义的危机性和它的投机性出现冲突，没办法形成循环”。当更底层的、物质性的生存矛盾（工、农、兵三种基本矛盾）的解决占据了人们更多的时间和精力，就无暇去生产和维持资本主义所依赖的那种抽象时间意识，系统于是就卡住了。\n\n[ANSWER]\n\n很多人认为，要颠覆一个腐朽的体系，最激进的方式就是“加速主义”，即推动其矛盾激化，使其更快地走向灭亡。这种想法看似彻底，却可能恰恰落入了体系自身的逻辑陷阱，因为资本主义本身就依赖于危机和投机的快速更迭与加速循环。\n\n追求让体系“卡住”，是一种完全不同的策略。资本主义的生命力在于它能将任何“危机”都迅速转化为新的“投机”机会，通过这种无缝衔接的循环来转移矛盾，延续其生命。所谓“卡住”，就是打破这种“危机-投机”的同步链条，让危机就是危机，无法再被轻易地转化为资本增殖的燃料。当这个循环被阻断，资本主义的时间链条就断裂了，它无法再顺畅地运转下去。这种“卡住”的状态之所以更可取，因为它不是盲目地加速破坏，而是让矛盾在无法转移的情况下充分暴露和成熟，为真正替代方案的酝酿创造了空间和时间。这种状态的实现，最终源于更底层的、更根本的生存矛盾的凸显——当人们不得不将全部精力用于解决劳动、生存、安全这些最基本的问题时，维系资本主义运转的那套抽象的时间和价值体系就失去了其生产的土壤，整个系统自然就卡住了。\n\n---\n\n[QUESTION]\n\n如果全球资本主义体系的内在矛盾最终会导致其“卡住”并可能崩解，那么作为身处其中的一员，我们应该如何准备？是投机取巧，在混乱中渔利，还是有其他的行动纲领？在这种准备中，最核心、最不能妥协的重点是什么？\n\n[THINK]\n\n此问题的核心线索是在预见的系统崩解面前，应采取的准备策略。其内在矛盾在于，一种是机会主义的、在资本逻辑内渔利的做法（如利用地缘冲突赚取铸币税或能源差价），另一种是国际主义的、以自我保全和解放为目标的准备。正确的机制是“未虑胜，先虑败”，即首先确保自身的生存和独立，建立“自保有余”的物质基础，而不是成为现有体系的另一个投机者。证据明确指出，不能像某些国家那样去“赚欧元的铸币税”或“卖天然气赚得盆满钵满”，而是要“做好准备”。准备的重中之重被明确为“粮食和能源”，这是生存的根本。其次是技术和交往。这一策略的边界在于，它要求在行动上首先聚焦于自身物质基础的稳固，之后才能谈及更高远的国际主义援助。\n\n[ANSWER]\n\n面对一个即将“卡住”并可能崩解的全球体系，一种常见的诱惑是投身其中，试图利用动荡为自己捞取好处，比如在能源危机中大发横财，或在地缘冲突中攫取金融利益。然而，这种做法只会让自己成为那个腐朽体系的一部分，最终一同被吞噬。\n\n正确的准备姿态，不是去做一个投机的“地缘气象派”，而是遵循“未虑胜，先虑败”的原则，做好我们自己的准备。这意味着，在考虑如何胜利之前，首先要确保自己不会失败。核心任务不是在资本的牌桌上玩得更好，而是要为这张牌桌随时可能整个翻倒的局面做好准备。这种准备的重中之重，是保障我们自己的生存与发展，具体而言，就是确保“粮食”和“能源”这两项最根本的物质基础。只有在“自保有余”——即不仅能自我保全，还有剩余力量——的前提下，当全球性的动荡来临时，我们才能不被卷入泥潭，并有能力去帮助那些在摊牌过程中被牺牲和被践踏的人。这是一种基于物质现实的底线思维，是为最终的解放做好坚实的铺垫，而不是在现行规则下追逐短期利益。"
    }
  ]
}