{
  "source_file": "input\\BV1cA4y197JT_【政治经济学】仅用一个公式，解决个人与社会，理论与现实的迷思_2022-04-12-01-01-14.txt",
  "analysis_history": [
    {
      "round": 1,
      "round_type": "基础分析",
      "result": "[QUESTION]\n\n我有个朋友，最近觉得生活太累，决定“躺平”了，不想再卷了。但他发现，自从他放弃奋斗后，非但没有得到安宁，反而他跟女朋友、跟家里的关系都变得特别奇怪和紧张。大家说话都客客气气的，好像在演戏，感觉关系的核心已经空了。为什么个人选择放弃努力，反而会导致最亲密的关系走向败坏？这到底揭示了维持一段关系需要什么样的代价？\n\n[THINK]\n\n定位到的现实问题是“躺平”导致社会关系恶化。线索是当事人选择“躺平”，停止个人奋斗。矛盾在于，其追求安宁的目标，却导致了亲密关系的紧张和空洞化。这背后的机制是个人所处的阶次决定了他能维持的社会关系的阶次，即“个人阶次 = 社会关系阶次 + 1”。当个人状态倒退，他所能维系的社会关系就会降级，从“生存”状态跌入“紧急状况”。原文的证据包括：个人“躺平”后，社会关系会“瓦解”或进入“危机状态”；这种状态下，关系只剩下“麻木不仁的表象”，为了维持表面的形式而牺牲了内在的实质。这个分析的边界在于，它揭示了社会关系是一种动态过程，需要持续投入，而非可以一劳永逸的静态资产。\n\n[ANSWER]\n\n人们通常把亲密关系看作是一个可以无条件退守的避风港，一个可以彻底放松、无需付出的地方。这种看法忽略了一个根本事实：任何社会关系都不是一个静止的物品，而是一个动态的过程，它会因为缺乏维系而衰败。\n\n当一个人选择“躺平”，他实际上是在主动降低自己所处的生命状态。这种个人的倒退并不会只发生在他自己身上，而是会直接冲击他身处的社会关系。一段关系不是一个固定的实体，它的活力水平取决于身处其中的个体的阶次。如果你的个人状态下降到仅仅是维持生存甚至自保的“紧急状况”，那么你所能支撑的社会关系，就必然会降格到更低的状态，即“危机状态”甚至“崩解状态”。这就是为什么事情会变得如此诡异。关系并没有立刻消失，而是进入了一种牺牲实质来维持空洞形式的危机模式。你会看到，对话变得肤浅，仪式变得毫无感情，所有人都在维持一种“麻木不仁的表象”。曾经存在的信任与爱，被用来牺牲，以保全关系表面的“完整性”，就像一个处于紧急状况的人为了保命而牺牲掉自己的肢体一样。\n\n因此，你的社会关系的健康状况，从来都不是独立于你个人奋斗状态的。生命本身就如逆水行舟，不进则退。\n\n---\n\n[QUESTION]\n\n历史上有些君主，或者现实中一些企业家，个人能力极强，权势和财富都在飞速增长，看起来非常成功。但奇怪的是，他们似乎永远被困在一种紧张的状态里，需要不停地收买人心、分配利益、搞权力平衡，仅仅是为了维持住自己的团队不散架。他们个人在“发展”，但他们所领导的组织或社会关系本身，似乎并没有任何质的提升和演变。为什么个人的成功，无法自动地转化为他所领导的社会结构的进步？他那些看似主动的、扩张性的行为，到底在维系着什么？\n\n[THINK]\n\n定位到的现实问题是成功的领导者（君主/企业家）无法使其组织进化。线索是领导者个人处于“发展”阶段，权势和财富不断增长。矛盾在于，领导者个人地位在提升，但他所管理的社会关系（忠诚链、雇佣关系）却停滞不前，仅仅是在“生存”。其机制在于“个人阶次 = 社会关系阶次 + 1”的原则。领导者处于“发展”阶次（二阶），这意味着他所能创造和维持的社会关系，最高只能达到“生存”阶次（一阶）。他的一切努力，本质上不是为了发展这个关系，而仅仅是为了让这个关系能够单调地再生产下去。原文证据包括：处于“发展”状态的君主，其能力仅仅是“维持他的忠诚链的生存”；他无法让这种君臣关系“升级”为亦师亦友的平等关系；他的行为只是为了维持，而不是发展。这个分析的边界在于，它适用于那些在一个既有的、惰性的或妨害性的秩序之内获得成功的个体，他们的发展是寄生性的，而非变革性的。\n\n[ANSWER]\n\n一个常见的迷思是，一个成功的领导者会自动地提升他所在的整个组织或社会。这种“进步主义”的庸俗看法，没有看到个人发展与他所处的社会结构演进之间存在着一个根本性的阶次落差。\n\n一个在既有秩序下权势不断增长的领导者，他个人正处在“发展”的阶次。然而，这种个人层面“发展”（二阶）的状态，仅仅赋予了他将其社会关系维持在“生存”（一阶）水平的能力。他那些永不停歇的活动——分封赏赐、收买忠诚、处理危机——其目的根本不是为了推动这个体系的进化，而是一种极其紧张的努力，仅仅是为了让他所依赖的社会关系（比如君主对将军的忠诚链，或者企业家与员工的生产关系）不至于崩溃。他所做的，只是在确保这种既有关系能够进行单调的、日复一日的再生产。这就是为什么一个君主，无论他个人变得多么强大，也无法将他与忠臣的关系从君臣之别，发展为平等的同志关系。他被那个让他得以发展的结构本身给困住了。他的成功，恰恰被定义为维持这种静态社会关系的能力，而不是将其演化为更高级形态的能力。\n\n所以，在一个给定的体系内，个人的发展在根本上只能服务于该体系既有关系的“生存”，而绝非其质的演进或解放。\n\n---\n\n[QUESTION]\n\n现在信息太多，各种观点满天飞，我们怎么才能有效地区分什么是真正有深度的“思想”，什么是人云亦云的“庸见”，以及什么是纯粹骗人的“谎言”或“意识形态”？它们表面上都在对现实发言，听起来都有道理。有没有一种结构性的方法，可以不陷入对其具体内容对错的争论，就能看穿它们之间的根本区别？\n\n[THINK]\n\n定位到的问题是如何区分“思想”、“庸见”和“谎言”。线索是这三者都对现实提出主张。矛盾在于，它们表面上看起来相似，但与实践/现实的结构性关系完全不同。其核心机制是“理论阶次 = 实践阶次 + 1”这个标尺。思想：理论比它能支撑的实践高一个阶次，一个“发展性”的理论（二阶）只能指导实践达到“生存”（一阶）。庸见：宣称理论与实践是同阶的（L(理论) = L(实践)），比如“我理论在发展，我实践也在发展”，这是一种妄想。谎言/意识形态：关系被颠倒（L(理论) < L(practice)）或被极度夸大。一个仅仅“自圆其说”的理论（一阶）却声称能带来“发展性”的实践（二阶），这就是谎言。原文证据包括：1）思想：具有自我批判性的“发展”理论，仅能维持实践的“自圆其说”（生存）。2）庸见：认为理论水平提高，实践能力就同步提高。3）谎言：一个仅仅“自圆其说”的理论，宣称能引导新社会关系的发展；或者一个修修补补的“发展性”理论，宣称能带来现实的“解放”。这个框架的边界在于，它评估的是一个理论对其自身效力所做的结构性宣称，是一种形式分析，而非内容分析。\n\n[ANSWER]\n\n我们通常试图通过判断一个观点的内容是否“正确”或“听起来有道理”来评价它，但这极易被操纵。真正的试金石，不在于一个观点说了什么，而在于它宣称自己与现实及实践之间是何种结构性关系。\n\n理论与它所能支撑的实践之间，从来不是对等关系；理论永远必须比实践高一个阶次。这个落差，就是区分三者的关键。**真正的思想**承认这个落差。例如，一个“发展性”的理论——即一个能够自我批判的理论——它只敢声称自己能让一种实践达到“生存”状态，也就是帮助一项行动变得稳定和可重复。与之相反，**庸见**则是一种对等的幻想：“我的思想在发展，所以我的实践能力也一定在发展。”这完全无视了当理论被投入到现实的泥潭时，必然发生的降阶。最后，**谎言或意识形态**则将这种关系彻底颠倒，它做出一种浮夸的承诺。比如，一个仅仅能“自圆其说”的理论（“生存”阶次），却宣称它能够引导实践走向“发展”；或者一个只能做些修修补补、局部批判的“发展性”理论，却吹嘘它能给现实世界带来彻底的“解放”。这是一种结构性的欺骗，无论其内容多么动听，因为它否认了从思想的内在世界走向行动的外部世界时，那个必然发生的“损耗”或“降阶”。\n\n因此，你可以识别一个谎言，不是通过它的内容，而是通过它所承诺的、那种在观念领域和现实领域之间不可能存在的高效率。\n\n---\n\n[QUESTION]\n\n一个非常辛劳的父亲，拼尽全力只是为了满足家庭的基本物质需求，他自己处在一种“生存”模式下。他当然爱自己的孩子，却发现自己完全没有耐心、时间或多余的精力去培养一种深刻的亲子关系，导致这个关系总是摇摇欲坠，充满危机。为什么在一个家庭里，成功地完成“生存”这个基本任务，似乎反而要以牺牲本应被这种生存所支撑的亲密关系为代价？\n\n[THINK]\n\n定位到的现实问题是处于“生存”状态的父母难以维系良好的亲子关系。线索是父母处于“生存”状态，专注于物质再生产。矛盾在于，父母的辛劳本是为了家庭，但作为核心的亲子关系本身却在受苦，处于危机之中。其机制是“个人阶次 = 社会关系阶次 + 1”的公式。父母的个人状态是“生存”（一阶），这意味着他所能维系的社会关系——亲子关系——必然处于更低的“紧急状况”（零阶）。他的全部精力都被自身的生存耗尽，没有盈余去投入到关系的发展中。原文证据包括：1）“非常辛劳的一个父亲”处于“仅是生存”的状态。2）他没有“时间、耐心或者富裕的预算来发展亲子关系”。3）因此，他的亲子关系“其实是很容易崩坏的”，这正是“紧急状况”的特征。他甚至可能为了孩子的生存（如上学）而牺牲自己的社会地位（求爷爷告奶奶），这是典型的“生存”模式下的交换。这个分析的边界在于，它描述的是一种结构性困境，而非个人品行问题，适用于个体资源被一个“妨害性”的社会大环境完全吞噬以维持自身存在的状况。\n\n[ANSWER]\n\n在这种情况下，人们很容易进行道德说教，认为这位父亲应该“更努力”地去和孩子沟通。但这完全忽视了那种将个人生存与社会关系的发展对立起来的结构性逻辑。\n\n这位辛劳父亲的处境，直接揭示了一个根本法则：你个人的生命状态，决定了你所能维系的社会关系的最高水平。当一个人处于“生存”状态（一阶）时，他的整个存在都指向了自身的物质再生产。他能让自己活下去，但也就到此为止了。根据这种结构性逻辑，这意味着他身处其中的社会关系，比如亲子关系，只能存在于下一个更低的阶次，即“紧急状况”（零阶）。这个关系因此变得常年脆弱，总在崩溃的边缘，因为这位父亲没有任何多余的精力、时间或资源可以投入到它的发展中去。他实际上是在用牺牲社会关系的质量，来换取自己肉体的生存。例如，为了让孩子能上学而去“求爷爷告奶奶”，这本身就是一种牺牲社会尊严以换取生存资源的典型行为。这里的悲剧在于，他在“生存”上的成功，恰恰是把亲子关系锁定在“危机”状态的原因。\n\n这揭示了，在匮乏和压力的条件下，个人的生存和亲密关系的发展，往往会变成相互竞争、而非相辅相成的目标。"
    }
  ]
}