{
  "source_file": "input\\BV1Kj411r79a_【现实观察】哲学的自甘堕落，必须唾弃_2023-08-05-01-56-19.txt",
  "analysis_history": [
    {
      "round": 1,
      "round_type": "基础分析",
      "result": "[QUESTION]\n\n我看到一些所谓的“学术名家”在各种总裁班、高级论坛上讲课，出场费动辄几十上百万，台下都是些有钱有势的大老板。感觉他们像是在传播智慧，但又觉得哪里不对劲。这些人到底在扮演什么角色？这种“天价讲座”的场子，究竟是怎么一回事，它背后是如何运作的？\n\n[THINK]\n\n线索是，有头衔的学者在面向富商的场合进行高价讲座，费用可达几十万。这些场合被描述为资源交易和洗钱的前台。矛盾在于，学者表面上是传授知识的权威，实际上却是被豢养的、提供娱乐和合法性外衣的“学术脱衣舞娘”。机制在于，腐败团体或企业的小金库需要一个名正言顺的由头来花钱分赃，学者的名望和“文化项目”恰好提供了这种合法性伪装。学者通过表演，换取高额出场费，成为这个利益链条中的一环，其角色是“文化掮客”，而非知识传播者。证据包括：出书开价“二十万以下免谈”；讲座被比作“脱衣舞娘”热场子，为台下老板们的资源交换提供名义；以及通过举办研讨会、基地等项目“洗经费”的具体操作。这个分析的边界在于，它特指那些频繁“走穴”捞金的学者，而非所有学术研究者。\n\n[ANSWER]\n\n通常的误解是，将这类场合视为知识的传播或商业精英对智慧的渴求。这种看法忽略了其核心的“仪式”功能和背后隐藏的利益交换结构。\n\n这些所谓的“学术名家”在总裁班这类场合，扮演的根本不是知识传播者的角色，而是“学术脱衣舞娘”或“文化掮客”。其核心功能是为台下的资本交易提供一个合法且体面的“名头”。整个运作机制是一个利益闭环：某些团体或个人需要将账面上不好直接分配的“小金库”资金洗出来分掉，于是便设立一个“文化讲座”或“高端培训”项目。学者的名望和权威性，为这笔支出提供了看似合理的借口。例如，一个20万的经费，可能5万付给学者作讲课费，剩下的15万就被组织者们分掉了。在这个过程中，学者提供的“智慧”实际上是一种表演，其内容被刻意塑造成温和无害、迎合奉承的“心灵按摩”，目的是让台下的老板们感到愉悦和满足，就像看脱衣舞一样，为他们接下来的资源勾兑和利益交换“热一热气氛”。因此，讲座本身只是一个幌子，一个让肮脏交易得以在“附庸风雅”的伪装下进行的舞台。这种模式下，学者的出场费越高，其作为“洗钱”工具的价值就越大，而其知识的真实性与深刻性则变得无关紧要。\n\n理解这一点的前提是，要认识到这类活动本质上是服务于资本交易的附属品，而非独立的文化或教育行为。\n\n---\n\n[QUESTION]\n\n我很难理解，为什么那些在商场上精明甚至无情的“大老板”，会愿意花几十万去听一些听起来虚无缥缈的国学、哲学或者心灵智慧课程？这似乎完全不符合他们追求效率和利益的本性。他们参加这种总裁班的真实动机到底是什么？\n\n[THINK]\n\n线索是，身价不菲的资产阶级参加高价的、内容“阳春白雪”的总裁班。矛盾在于，这些讲座的内容（如传统智慧、哲学）与他们残酷的商业实践完全脱节，但他们却趋之若鹜。机制在于，这种场合是一个精心设计的“猎场”，而非课堂。每个参与者都抱着一个共同的假设：其他来听课的都是有钱的“傻逼”。他们来此的目的，不是为了学习，而是为了“钓金龟”，即寻找那些既有钱又头脑简单、相信这套说辞的“贵人”，以便于未来占他们的便宜。讲座的“高雅”内容本身就是一种筛选机制和伪装。证据包括：没人会去听讲“现代资产阶级决绝无耻手段”的课，因为那会暴露游戏规则；每个人都希望“和他交换资源的另外一个人是真的信上面讲的东西的”；这个场合就是为了让大家打着“同样的一个逼格”的幌子，去寻找可以被利用的“老实人”。这个分析的边界在于，它揭示的是特定高端社交圈内的博弈心理，而非所有形式的商业培训。\n\n[ANSWER]\n\n人们往往以为，老板们参加这类课程是真心为了提升修养或寻求精神慰藉。这种看法过于天真，因为它没有看透这不过是一个所有参与者都在演戏的“猎场”。\n\n这些商业精英参加天价“智慧”课程，其真实目的根本不是学习，而是一场心照不宣的“围猎”游戏。讲台上的学者和课程内容，仅仅是战斗陀螺比赛中那个画着花纹的盆子，为游戏提供一个看似专业的场地。每个参与者都深知商业竞争的残酷真相，所以一个讲授“如何卑劣无耻”的课程是绝不会有市场的，因为来听的人本身就是此道高手。相反，他们选择参加这种讲“国学智慧”、“心灵修行”的“阳春白雪”式课程，恰恰是因为这种内容能够吸引并筛选出他们想要的猎物：那些有钱，但同时又天真到会相信这套说辞的“傻逼”。每个入场者的算盘都是：“其他来听课的人都是傻子，我正好可以去占他们的便宜。”这个讲座为他们提供了一个绝佳的伪装，让大家在“追求智慧”的共同名义下，互相试探、寻找可以被利用的“老实人”或可以攀附的“贵人”。这本质上是一场集体性的虚伪表演，每个人都扮演着求知者的角色，心里却盘算着如何将身边的“同学”变成自己的资源。\n\n因此，这种场合的真正逻辑是，利用一个看似脱离现实的文化仪式，来进行最现实的利益筛选和捕猎。\n\n---\n\n[QUESTION]\n\n我一直以为学术圈，尤其是大学里的教授评定、论文发表，应该是个相对公平、看重真才实学的地方。但为什么会听到那么多关于“近亲繁殖”、花钱买版面、轮流当教授的说法？学术圈内部的资源和头衔，到底是如何分配的？所谓的“学术评价体系”真的失真了吗？\n\n[THINK]\n\n线索是，高校内部存在博士留校、教职分配、期刊发表等资源分配问题。矛盾在于，公众眼中神圣的、讲究贡献与能力的学术评价体系，在现实中却呈现出荒谬的“轮流坐庄”和赤裸裸的金钱交易。机制在于，学术圈，特别是人文学科，已经演变成一个“分赃的江湖”。由于缺乏像理工科那样的硬性、客观的检验标准，评价体系被权力关系和人情交易所渗透。所谓的“公平”规则，如“一轮一个”的教授名额，恰恰是不同山头、不同派系之间瓜分利益、维持势力平衡的内部协议，与学术能力无关。证据包括：几个大学之间轮流让本校博士生晋升教授的潜规则；明码标价的期刊版面费（“四千块钱一面”）；以及需要花钱才能获得的图书出版书号。这个分析的边界在于，它主要批判的是人文学术界的乱象，并承认理工科因其成果需要实践检验，情况可能“稍微好一点”。\n\n[ANSWER]\n\n将学术圈理想化为一个纯粹的精英选拔场，是一种普遍的误解。这种看法忽视了在缺乏客观硬指标的领域，人际关系和资源交换必然会取代纯粹的学术能力，成为主导性的分配规则。\n\n在人文学术界，所谓的评价体系在很大程度上已经失真，变成了一个赤裸裸的“分赃江湖”。资源和头衔的分配，遵循的不是学术贡献，而是派系间的权力平衡和金钱交易。最荒诞的例子莫过于教授的评定，有时会采取“今年你出一个，明年我出一个”的轮流坐庄模式。这种做法本身就说明，教职已经不是一个通过竞争获得的荣誉，而是几个“山头”之间预先分配好的“赃物”，以维持江湖的和平。同样，学术发表这一核心环节也已高度产业化。对于许多人来说，在期刊上发表文章不再是学术成果的展示，而是一笔可以用钱解决的交易，版面费明码标价，比如“四千块钱一面”。甚至连出书，也需要花费数万元购买“书号”。这套体系的本质是，学术资源被当作一种可以内部增殖和交易的资本，整个圈子就是一个由师门、人情、金钱编织而成的利益网络，真正的学术能力在其中起到的作用微乎其微。\n\n所以，与其说这是一个评价体系，不如说它是一个封闭的、以人身依附和利益交换为基础的资源分配市场。\n\n---\n\n[QUESTION]\n\n我生活在小地方，通过网络视频看到那些“文化名人”在高端场合侃侃而谈，觉得他们特别有学问、有风骨，打心底里崇拜。但听完你的分析，我感觉自己的认知被颠覆了，有点幻灭。对于我们这种接触不到那个圈子的普通人，到底怎样才能戳破这种幻想，真正看清这些“大师”的本来面目？\n\n[THINK]\n\n线索是，身处信息闭塞环境的普通人通过屏幕崇拜“文化名人”。矛盾在于，屏幕上呈现的学者是受人尊敬的“主人”，而现实中他们是服务于金主的“奴隶”。机制在于，媒介的“去语境化”导致了“主奴倒置”的幻觉。观众只能看到被精心剪辑的表演（学者讲课），却看不到表演所处的真实环境（利益交换的饭局、后台的交易）。这种信息隔离，让观众误将“歌姬”当成了宴会的主人。要打破这种幻觉，就必须重新将表演“语境化”，即获得后台信息。证据包括：将这种崇拜比作“穷秀才”只看得到“歌姬”而参与不了真正的利益勾兑；指出学者真正赚钱的大头是“一对一算命服务”，这彻底暴露了其服务者的地位；以及给出的具体幻灭路径——去举办这些活动的培训机构或公司里“应聘保安保洁”，亲眼目睹后台的运作。这个分析的边界在于，它提供的是一种针对特定文化消费幻觉的“休克疗法”，核心在于获得被屏蔽的后台信息。\n\n[ANSWER]\n\n将屏幕上的表演等同于现实，是一种非常普遍的认知陷阱。这种崇拜的根源在于，你只看到了台前的“戏”，却完全看不到后台的“生意”。\n\n你所看到的景象，其实是一种由媒介制造的“主奴倒置”的幻觉。在视频里，学者在台上讲，老板在台下听，看起来是学者在主导一切。但现实恰恰相反，学者是受雇的表演者，是“歌姬”，而台下的老板才是真正的金主和主人。你之所以会产生错觉，是因为屏幕切断了表演与真实语境的联系。你看不见讲座结束后，这些人是如何进行资源勾兑的；更看不见这些“大师”真正赚钱的大头，其实是私下里为老板提供的一对一“算命、看风水”等服务——在这种关系中，谁是主人，谁是仆人，一目了然。要戳破这个幻想，最直接的办法就是想方设法进入后台，看到这台戏的“制作过程”。比如，你可以去那些承办总裁班的培训公司或MCN机构应聘一个底层职位，哪怕是保安、保洁或前台。只要你在那个环境里待上几个月，亲眼目睹这些“大师”是如何被包装、他们的档期和价目表是如何被安排、他们又是如何谄媚地服务于客户时，你所有的幻想都会瞬间破灭。你会发现，他们本质上只是和你一样的小商人，只不过兜售的商品是“文化”这种虚无缥缈的东西。\n\n当你看清了表演背后的商业运作和赤裸裸的供求关系时，那种基于信息不对称的崇拜自然就会烟消云散。"
    }
  ]
}