{
  "source_file": "input\\BV1uK42147u7_【现实观察】如何看待那位勇敢而无罪的国际主义者_2024-03-03-01-46-38.txt",
  "analysis_history": [
    {
      "round": 1,
      "round_type": "基础分析",
      "result": "[QUESTION]\n\n一个身处强大体制内部的人，因为无法忍受其残忍和丑陋，选择了一种极端的、旨在引发媒体舆论的抗议方式。这种看似充满勇气的激烈行动，为何被评价为一种“可惜的”且力量不足的斗争方式？在这种分析框架下，真正能够“击中要害”的有效反抗，应该具备哪些完全不同的特征？\n\n[THINK]\n\n该行动的核心线索是，一名体制内情报人员采取了借助媒体舆论的极端个人抗议。其内在矛盾在于，行动的激烈程度和道义感召力很强，但被判定为对体制的实际威胁“并不足够”。这背后的机制是力量类型的错配：行动试图用“舆论资本主义”或“视讯性丑闻”这类非物质性的、符号性的力量，去对抗一个以国家机器、军队和情报部门等实体暴力为基础的“帝国主义”权力结构，因此在力量对比上存在根本性的劣势。原文证据包括：1）明确指出“光凭媒体舆论，光凭这种视讯性的丑闻，力量并不足够”；2）这种方式被定性为“借助媒体舆论倒逼”；3）其本质被视为一种“绝望的表达”和“受限的行动路线”。此分析的边界在于，它针对的是一个组织严密、掌握强大实体力量的“帝国主义老巢”，对于其他类型的权力主体，舆论的效力可能会有所不同。\n\n[ANSWER]\n\n通常，人们倾向于将这类充满道义感的激烈个人抗争视为英雄壮举，但这种看法往往忽略了行动策略与斗争目标之间是否匹配的关键问题。评价一场抗争是否有效，不能只看其决心，更要看它是否触及了对手权力的根基。\n\n这种抗争方式被视为力量不足，其根源在于一种战略上的错位。它本质上是试图运用“舆论资本主义”或“视讯性丑闻”这类符号性的力量，去对抗一个以国家暴力机器为核心的“帝国主义”实体。这种权力结构的基础是军队、情报系统和国家机器，而非公众形象或道德声誉。因此，仅仅制造一场媒体风暴，虽然能引发关注，却无法从根本上动摇对方的力量根基，最终沦为一种“绝望的表达”和“受限的行动路线”下的报复。这种斗争形态被认为是无力的，因为它没有办法组织一个国家、建构一支军队，去真正阻止不义之举的发生。相比之下，一种更成熟、更具威胁的斗争形态，应当是直接作用于对方的实体力量。它需要更理性、更审慎的策略，例如，利用内部身份进行更大规模、更具破坏性的情报泄露，直接打击其“脏器甚至心脏”。这种行动需要一个“更有力的支点”和“更强大的支撑”，即一个能够提供周密保护和接应的组织。\n\n因此，这种分析框架强调，有效的反抗必须在力量的层级和类型上与对手相匹配，而不是停留在符号层面的对抗。\n\n---\n\n[QUESTION]\n\n当一个体制内的反叛者下定决心行动时，他往往会寻求志同道合的社群支持。然而，他所能接触到的“无政府主义”或“极端自由主义”社群，为何被描述为是“无力的”，甚至在根本上无法提供真正的支撑？一个真正“强而有力”的支撑社群，必须提供哪些具体的、超越思想共鸣的要素？\n\n[THINK]\n\n此问题的线索在于，一名体制内反叛者所处的社群无法为其提供有效支持。其核心矛盾是，社群在意识形态上与他亲近，但在实际行动中却“无力”。这背后的机制在于社群的组织形态和阶级属性。这类社群被定性为“完全游牧化的”、“极端自由主义的变种”，其本质上仍是“资产阶级资本主义的”，组织形式松散，类似于“市场为主体的资讯同好团体”或“娱乐cosplay同好团体”。这种结构决定了它无法提供高强度、高风险行动所必需的严密组织、物质资源和安全保障。原文证据包括：1）直言这类社群“没有办法组织一个国家，没有办法去建构一支军队”；2）指出其无法为行动者及其家人提供“强而有力的保护措施”和“相应的庇护”；3）将其比作同好团体，缺乏“强而有力的线下的支撑点”。此判断的边界在于，它评价的是社群在支持高风险、颠覆性政治行动上的能力，而非其在一般社会动员或文化活动中的作用。\n\n[ANSWER]\n\n人们往往认为，找到一个理念相同的社群就能获得支持，但这混淆了思想上的同情与行动上的支撑这两种截然不同的功能。一个社群能否提供真正的力量，关键在于其组织形态和所能调动的资源，而非仅仅是成员间的思想共鸣。\n\n这类社群之所以被视为“无力的”，根源在于其组织上的“游牧化”和本质上的松散。它们被描述为一种“极端自由主义的变种”，其结构类似于基于市场逻辑的“资讯同好团体”，甚至是“娱乐cosplay同好团体”。这种社群缺乏严密的组织纪律和强大的资源调动能力，因此无法为身处险境的个人提供最关键的保障。它既不能“建构一支军队”来形成实质性对抗，也无法为行动者的家人提供“相应的庇护和帮助”，而这恰恰是让行动者瞻前顾后、无法采取更深入行动的核心障碍。这样的社群最终只能提供意识形态上的俘获，而无法转化为真正的行动力。一个真正“强而有力”的支撑点，必须超越思想共鸣，提供三个层面的具体支持：强有力的意识形态指引以坚定其信念；强而有力的“线下的支撑点”以提供物理空间和资源；以及最重要的，能够为行动者及其家人提供“强而有力的保护措施”的组织能力，从而解除其后顾之忧。\n\n说到底，一个社群是否强大，不取决于其口号的激进程度，而取决于它能否为成员提供对抗系统性风险的现实庇护。\n\n---\n\n[QUESTION]\n\n一位接触到“帝国主义”内部丑陋真相的情报人员，其最终的抗争被评价为一种“惋惜”和“浪费”，认为他本可以做得更多。这种“惋惜”的情绪究竟指向什么？它揭示了一种怎样的理想行动者画像？以及，要如何将这类潜在的“漂泊无依的国际主义战士”从悲剧人物转变为真正的“解放者”？\n\n[THINK]\n\n此问题的线索是，一名情报人员的抗议行动被视为“可惜”和“浪费”。其核心矛盾在于，他以生命为代价进行了勇敢的抗争，却被认为没有发挥出全部潜力，其行动路线存在局限。这背后的机制是个人潜能与行动策略的错配。作为一名“美军空军的情报人员”，他拥有直接接触“帝国主义”核心机密的独特优势，其最大价值在于利用这一优势进行更具破坏性的内部打击。然而，他最终选择的公开、一次性的悲剧性行动，被视为一种因缺乏更好出路而导致的“受限的表达”，浪费了持续造成实质性伤害的可能。原文证据包括：1）明确指出“他能做的事情是远远多于这种事情的”；2）惋惜他最终“无路可走，只能这样走”；3）理想的行动是“更深入的、更直接的、更赤裸裸的击中帝国主义丑陋”心脏的机会。此评价的边界是，它完全从“务实的国际主义者”追求对敌对势力造成最大化实质性损害的功利角度出发，而非从个人道德或精神象征意义的角度。\n\n[ANSWER]\n\n将一次决绝的抗争评价为“惋惜”，并非否定其动机的纯洁或个人的勇敢，而是从一种冷峻的战略视角出发，对其行动所产生的实际效果与个人潜能进行对比后得出的结论。这种惋惜指向的是一种巨大潜能的错付与浪费。\n\n这种分析认为，该行动者的悲剧在于，他独特的身份优势没有被转化为最有效的打击力。作为一名“美军空军的情报人员”，他所掌握的“丑陋真相”和内部渠道，是比任何外部抗议者都更具杀伤力的武器。他本可以成为一个持续对“帝国主义”脏器进行精准打击的内部爆破手，例如进行更大规模、更具毁灭性的情报泄露。然而，他最终的行动却是一种公开的、一次性的、带有“绝望表达”性质的悲剧，这被看作是在“行动路线受限”的情况下一种无可奈何的选择，而非主动的、最优的战略出击。理想的行动者画像，是一个能够将理想主义转化为“温和而有力的现实”的“解放者”，他应当自己去行动，而不是用死亡去“呼吁别人”行动。要实现这种转变，关键在于外部力量的介入。需要有一个强大的组织去主动“策反”和“接应”这些在敌营中“漂泊无依的国际主义战士”，为他们提供全方位的支持，尤其是“家人的安全保障”和“一整个社群共同体的信赖”，让他们有能力、有底气去执行更理性、更审慎、也更具破坏力的长期斗争策略。\n\n本质上，这是要将个人的道德觉醒，通过强大的组织支持，转化为一种可持续的、具有现实破坏力的政治行动，从而避免其沦为一场无可挽回的个人悲剧。\n\n---\n\n[QUESTION]\n\n文中提出了“务实的国际主义”与“纯粹浪漫的”国际主义（如无政府主义或托洛茨基主义）的对立。既然两者都可能源于一种反对压迫的“国际主义精神”，那么“务实”与“浪漫”的根本区别究竟体现在哪里？这种“务实”的路线，在组织形态、力量来源和最终目标上，展现出怎样一种截然不同的政治想象？\n\n[THINK]\n\n此问题的线索是“务实的国际主义”与“浪漫的国际主义”之间的对立。其核心矛盾在于，两者共享相似的起点（国际主义精神），却走向了被判定为“有力”与“无力”的截然不同的道路。这背后的机制在于对“力量”的理解和运用方式的根本分歧。“浪漫的”路线被描述为“游牧化的”，它拒绝“沉淀着的力量”，幻想借助“资本主义的一些新形态”（如舆论、媒介）来解决力量对比的悬殊问题，本质上是唯心的。“务实的”路线则是唯物主义的，它坚持力量只能用力量来对抗，因此必须建立一个能够与“跨国资本家的母巢的大型国家”相抗衡的实体，即以“国家作为它的策源基地”。原文证据包括：1）“务实”路线明确需要一个“能够对垒的，以国家作为它的策源基地的”实体；2）批判“浪漫”路线“妄图去借助资本主义的一些新形态”去“解决力量对比”；3）强调“务实”路线要“尽一切努力”，而不是“隔岸观火”。此分析的边界是，它预设了全球斗争的核心是与强大的国家机器的对抗，因此将建立对等的国家级实体作为唯一务实的选择。\n\n[ANSWER]\n\n人们常常将所有具有反叛精神的国际主义混为一谈，但“务实”与“浪漫”之别，揭示了在如何理解和运用“力量”这一核心问题上存在着深刻的鸿沟。这并非精神高下之分，而是现实策略的根本对立。\n\n“浪漫的”国际主义，如某些无政府主义或托洛茨基主义变体，其核心特征是“游牧化”和对现有权力结构的排斥。它倾向于相信可以通过非实体性的、流动的方式改变世界，例如幻想借助“舆论资本主义”或“指数资本主义”等资本主义自身演化出的新形态，来颠覆力量对比。这种路线被视为“纯粹浪漫”，因为它回避了建立“沉淀着的力量”这一艰巨任务，其社群是无力的，无法真正危及对手。相比之下，“务实的国际主义”则是一种彻底的现实主义。它承认力量的物质性，认为要对抗一个以“大型国家”为“母巢”的全球资本体系，就必须建立一个同等级别的物质力量。其政治想象的核心，就是要建立一个同样以“国家作为它的策源基地”的强大实体，用有组织的力量去对抗有组织的力量。这种路线拒绝“隔岸观火”，它要求主动出击，进行意识形态输出乃至“革命的输出”，并为在敌营中的战士提供包括家人安全在内的全方位物质与组织保障。\n\n归根结底，“务实”与“浪漫”的根本区别在于：前者坚持必须掌握和运用国家层级的实体力量来赢得斗争，而后者则试图绕过这一残酷的现实，寄望于在现有体系的缝隙中寻找颠覆的可能。"
    }
  ]
}