{
  "source_file": "input\\BV1VDubz5EKp_【7月14日场第九位】无锡俱乐部成员询问家庭和俱乐部之间该怎么选？_2025-07-16-20-13-41.txt",
  "analysis_history": [
    {
      "round": 1,
      "round_type": "基础分析",
      "result": "[QUESTION]\n\n我是一名俱乐部成员，同时也需要承担家庭责任。我感到很矛盾，因为俱乐部似乎要求成员付出很多，这让我觉得必须在它和我的家庭之间做出选择。请问，应当如何理解个人家庭责任与对一个集体组织的承诺之间的关系？\n\n[THINK]\n\n这个问题的核心是青年在“家庭”与“俱乐部”两个责任主体之间的撕扯感。常规思路可能会平衡二者，或者强调一方的重要性。但作者的分析是颠覆性的，他没有将两者对立，而是建立了一个“人性-革命性”的因果链条，从而重新定义了俱乐部的功能。我的回答策略是：首先，指出将二者对立是一种普遍的误区。其次，深入阐释作者的核心论证——即对家庭的责任是“人性”的基石，而一个组织如果要求成员泯灭人性，那么这个组织本身就是病态的，其所谓的“革命性”也是虚假的。最后，点明作者给出的出路：俱乐部不应是家庭的替代品或竞争者，而应是一个旨在帮助成员更好地履行家庭责任的互助工具，其目标是改善成员的现实生活状况。\n\n[ANSWER]\n\n将家庭责任与集体承诺视为一组不可调和的矛盾，并为此感到撕裂，这本身就是一种被误导的困境。这种想法将集体组织错误地定位为一个需要你牺牲个人生活来效忠的抽象实体，从而制造了不必要的精神内耗。\n\n你的痛苦并非源于你对家庭的责任感过重，而是源于对集体组织功能的根本性误解。分析的核心在于“破”与“立”两个层面：\n\n首先，它“破除”了将“集体性”置于“人性”之上的虚假道德。论证指出，一个人如果连自己的家人、爱人都不优先去呵护和保障，那么他所谓的“集体性”或“革命性”就是无源之水、无本之木。一个连基本人性都丧失的人，其对集体的忠诚是不可信的，他今天能背叛家庭，明天就能以同样的方式背叛集体。因此，要求成员牺牲家庭责任的组织，本身就是在进行一种情感与道德绑架，其根基是病理化的。\n\n其次，它“建立”了集体组织的正确功能定位。集体或俱乐部存在的根本目的，不是让你逃离现实责任，画地为牢，而是作为一个互助平台，帮助你更有效地面对现实。它的目标应当是切实地降低你的生活成本、提高你的个人能力、改善你的就业状况，最终让你有更多资源和盼头带给家庭。它是一个工具，服务于你作为一个具体的人的全面发展，而不是一个需要你献祭个人生活的偶像。\n\n因此，真正的出路在于重新校准你对集体功能的认知。你参与集体的行动，其成果必须能够转化为你个人能力、精神面貌和家庭关系的实际改善，否则这个集体就已经走向了它的反面。\n\n---\n\n[QUESTION]\n\n我的父母为了赚钱，对自己剥削得非常狠。每当我参加俱乐部聚餐这类非生产性的活动时，我都会产生一种强烈的愧疚感，觉得自己没有像他们一样拼命，没有为他们多存养老钱。这种愧疚感让我很痛苦，这是不是意味着我应该放弃这些活动，更投入地去工作？\n\n[THINK]\n\n青年的困惑表面上是关于“愧疚感”的道德挣扎，他将其归因于对父母的亏欠。作者的分析则是一次犀利的精神外科手术，直接剖开“愧疚”的表皮，暴露出其下隐藏的真正内核——“失败感”与“羞耻感”。我的回答策略是：首先，点明将这种痛苦归结为“愧疚”是一种自我美化的道德掩饰。其次，详细拆解作者的论证，揭示这种感觉的真正来源：它并非源于对父母的爱，而是源于对自己社会地位低下的羞耻，以及对“人上人”生活的隐秘欲望。与成功人士的高端社交相比，俱乐部廉价的聚会让他感到失败。最后，指出作者提供的解决方案：停止用“愧疚”这种道德词汇来伪装，直面自己内心深处的欲望与愤懑，承认这并非“家庭与俱乐部”的二选一，而是“成为人上人与接受现状”的二选一。\n\n[ANSWER]\n\n你将这种痛苦的情感命名为对父母的“愧疚”，这是一种普遍的、用以掩盖更深层焦虑的心理机制。它让你看起来像一个有道德感、有孝心的人，但这层温情脉脉的糖衣包裹的，却是一个关于失败与羞耻的苦涩内核。\n\n这种感觉的根源，并非你对父母的亏欠，而是你对自己现状的极度不甘。分析为你揭示了这层被巧妙伪装的真相：\n\n它“破除”了“愧疚感”这一道德幻觉。论证指出，这根本不是愧疚。真正的愧疚是对他人造成伤害后的悔恨，而你的感受指向的完全是你自己。你的父母之所以那么拼命，恰恰是因为他们对你无法指望。你的存在没有让他们过上舒坦日子，这让你感到的不是愧疚，而是羞耻、耻辱和丢脸。你不是在为他们难过，你是在为你自己的失败而痛苦。\n\n它“建立”了对痛苦来源的真实诊断——“失败感”。这种挫败感在你参加俱乐部活动时被急剧放大。因为你潜意识里将眼下“几个穷哥们在小餐桌上吃饭”的社交，与想象中“成功的男人”出入高端酒会、坐拥香车美女的场景进行对比。这种巨大的落差让你感到羞耻。因此，你所谓的“愧疚”，只是为了掩盖这种郁郁不得志的愤懑，以及你内心对更高、更体面生活的欲望所制造出的道德烟幕。你的核心矛盾，并非“俱乐部与家庭”的二选一，而是“俱乐部所代表的现实”与“成为人上人”的渴望之间的二选一。\n\n所以，解决问题的第一步，是停止用“愧-疚”来欺骗自己。你需要诚实地面对那种源于社会比较的失败感，并承认自己内心深处的欲望。\n\n---\n\n[QUESTION]\n\n看到俱乐部人少、资源匮乏的现状，我很想为集体做点事，觉得自己应该多“贡献”一点。但同时我又感到无力，因为我本身也没什么资源可以贡献。在这种集体处于弱势的情况下，作为成员，我的首要任务难道不应该是尽我所能地去奉献和牺牲吗？\n\n[THINK]\n\n青年将“贡献”视为一种在集体困境中的道德责任，这是一种常见的、带有悲情色彩的思维定式。作者的分析彻底颠覆了这种观念，用“自强不息”取代了“贡献”。我的回答策略是：首先，指出在弱势状态下谈论“贡献”是一种有害的自我感动。其次，阐明作者的核心论证：作者通过“拔三根毛的秃头”这个比喻，辛辣地指出了弱者之间的“贡献”是毫无意义的内耗，它解决不了任何实际问题。真正的出路不是向内索取，而是向外拓展。最后，揭示作者给出的行动纲领：停止扮演贡献者，转而成为一个“自强者”。成员的首要任务是先让自己强大起来，去外部世界学习技能、积累资源，当自己成为有能力的人（“富哥”）之后，再回来反哺集体。这时的“贡献”才是有意义的。\n\n[ANSWER]\n\n将“贡献”和“牺牲”视为弱势集体中成员的首要道德义务，这是一种极具迷惑性的陷阱。它看似高尚，实则是一种通过制造“人间惨剧”景观来维系虚假团结的病态逻辑，最终只会导致集体性的沉沦。\n\n你这种想要“贡献”的冲动，其根源并非真正的集体主义，而是一种对自身无能的错误补偿。分析从根本上重塑了“贡献”的定义：\n\n它“破除”了弱者“贡献”的价值幻觉。论证一针见血地指出，当你只剩下“三根毛”时，拔一根出来“贡献”是毫无意义的。这种行为非但不能解决问题，反而是在扮演一个“最大贡献者”的角色，进行道德绑架。集体需要的不是这种三瓜两枣式的、自我感动式的牺牲，因为这解决不了根本问题，反而会耗尽本就稀缺的能量。\n\n它“建立”了以“自强不息”为核心的行动原则。真正的出路不是让你“贡献”，而是让你先“强大起来”。你的首要任务不是从干涸的池塘里再舀一勺水给别人，而是自己先去找到活水。这意味着你需要先去好好工作、劳动，把自己的能力锻炼起来，在现实世界中站稳脚跟。当你通过自己的双手挣到钱、掌握了技术，成为了一个有资源、有能力、有眼光的人，你才真正拥有了“贡献”的资格。\n\n因此，真正的贡献，是在你功成名就、有了选择权之后，依然愿意回来拉兄弟们一把。这种基于能力的扶持，才是坚实和平等的，而不是基于弱势的相互怜悯。这个选择权，才是检验你对集体忠诚度的唯一标准。\n\n---\n\n[QUESTION]\n\n我明白了简单的聚会无法提升能力，现在我打算专注投入到技术学习和工作中去。但这需要耗费大量时间，并且我必须在资本主义的职场里去“卷”。这让我感到困惑，我似乎是在用一种我们所批判的逻辑来提升自己，这与我们建立俱乐部、试图逃离这个体系的初衷是否背道而驰？俱乐部的真正作用到底是什么？\n\n[THINK]\n\n青年陷入了一个经典的“目的与手段”的悖论：为了达成反体系的目标，却不得不使用体系内的手段。作者通过一个精妙的“监狱”比喻，厘清了俱乐部、个人发展与最终目标之间的关系。我的回答策略是：首先，指出将俱乐部视为一个与外部世界隔绝的“避难所”或“飞地”是根本性的错误。其次，深入解析作者的“监狱”模型：外部的资本主义职场是大监狱，而俱乐部绝不能成为大监狱里一个“更小的、供狱友抱团取暖的监狱”。最后，阐明作者给出的俱乐部定位：俱乐部是“越狱”的指挥部和思想根据地。成员必须进入大监狱（职场）去和“牢头”周旋，目的是偷取越狱的工具（技术、资金、信息）。俱乐部存在的意义，就是不断提醒成员“越狱”的最终目的，确保他们不会在偷工具的过程中，沉溺于在监狱里当个小头目，从而丧失了逃出去的意志。\n\n[ANSWER]\n\n你所面临的“在体系内卷，以求反体系”的困惑，源于一个核心的定位错误：你将俱乐部想象成了一个可以与外部世界完全切割开的“自由领地”。这种想法是致命的，因为它会把一个旨在解放的组织，变成一个自我封闭、与世隔绝的“小监狱”。\n\n要走出这个思想困境，必须理解俱乐部在整个斗争格局中的真实角色。分析为你提供了一个清晰的“越狱”模型：\n\n它“破除”了俱乐部作为“避难所”的幻想。论证用“监狱”作比，辛辣地指出：在一个大监狱里，几个狱友再挖一个小监狱躲进去，并宣称这里是自由的，这是疯了。俱乐部如果只是一个让成员逃避现实、相互慰藉的空间，那它就失去了存在的意义。它的功能不是让资本主义的压迫“失效”，而是让你找到挣脱枷锁的“希望”和“方法”。\n\n它“建立”了俱乐部作为“越狱指挥部”的功能定位。你的目的，是和一群狱友一起“越狱”——即从资本主义的奴役异化关系中逃离出去。而越狱的工具（技术、资源、经验），恰恰散落在监狱的各个角落，甚至在“牢头”手中。因此，你必须进入职场这个“大监狱”去行动，但你的目的不是为了在监狱里获得更好的待遇，而是为了偷偷获取“小勺子”、“指甲剪”等越狱工具。俱乐部就是那个不断为你明确“越狱”这个最终目标、分享“工具”信息、协调“越狱”计划的地方。它提供的是正确的“指导思想”。\n\n所以，你当前去努力学技术，不是背离初衷，而恰恰是“越狱”计划的一部分。关键在于，你必须时刻保持清醒：你所做的一切，是为了最终和兄弟们一起砸开牢门，建立一个按劳分配的合作社，而不是为了在监狱里混得风生水起。"
    },
    {
      "round": 2,
      "round_type": "深度分析",
      "result": "[QUESTION]\n\n我感觉很矛盾。一方面，我要承担家庭责任，父母为了赚钱对自己那么狠，如果我不能多赚钱让他们过上好日子，我就会有愧疚感。另一方面，俱乐部也需要成员付出很多，但现在人太少，感觉没什么成果。我哪怕只是去参加个聚餐，都会有这种愧疚感，我该怎么在家庭和俱乐部之间选择？\n\n[THINK]\n\n来访者将他的困境表述为在“家庭责任”与“俱乐部义务”之间的道德选择。他用“愧疚感”来命名自己在参与俱乐部活动时的感受，并将其归因于未能像父母一样自我剥削以赚钱。这种“愧疚”的叙事，实际上是一种情感置换。核心冲突并非外部的责任冲突，而是内在的价值冲突：他渴望世俗意义上的成功，但现实却无法满足这种渴望。他所体验到的不是对父母的愧疚，而是面对自身社会地位低下、成就感匮乏时产生的羞耻与挫败感。俱乐部本应是提升能力的场所，如今却成了映照他“失败”处境的一面镜子，聚餐的“寒酸”与他想象中成功人士的“高端酒会”形成鲜明对比，这才是情绪的真正来源。他用“愧疚”这一更具道德色彩的词汇，来掩盖对自身现状的羞耻和对“人上人”生活的欲望。此分析的前提是，他所描述的“愧疚”确实与休闲活动而非具体的不当行为相关联。\n\n[ANSWER]\n\n你面临的问题，看似是家庭与俱乐部之间的责任分配，但真正的纠结并非源于此。你反复提及的“愧疚感”，其实是一种巧妙的伪装，它掩盖了一种更深、更刺痛你的感受：羞耻感。\n\n你看到父母的辛劳，这在你心中树立了一个标杆——只有拼命赚钱，才是有价值的。因此，当你参与俱乐部聚餐这种“不产生金钱”的活动时，你感到的并非是对父母的亏欠，而是对自己无能的羞耻。那个小小的餐桌，让你看到的不是同伴情谊，而是与你内心渴望的“高端酒会”、“海景房”之间的巨大鸿沟。\n\n你并不是在为父母愧疚，你是在为自己感到失败和挫败。\n\n“愧疚”听起来很高尚，像一个孝子的自责，而“羞耻”则难以启齿，因为它直指你对自己现状的不满和对更高社会地位的欲望。所以，你无意识地选择了前者来包装后者，让自己看起来更“干净”。你真正要做的选择，不是在家庭和俱乐部之间，而是在直面自己对成功的渴望与用道德感来逃避这种渴望之间。这个选择的前提，是你是否愿意承认，那份“愧疚”的背后，藏着一个渴望成为“人上人”的自己。\n\n---\n\n[QUESTION]\n\n我觉得俱乐部现在最大的问题是人太少了，需要成员付出很多才能维持。我也想多做点贡献，但感觉使不上劲。如果人多一点，是不是就能吸引到一些有本事、有资源的人，情况就会好起来？我们应该怎么做才能让俱乐部发展起来？\n\n[THINK]\n\n来访者将俱乐部发展不力的原因归结为外部资源的匮乏，即“人太少”，并认为解决方案是引入更多人，特别是“有本事的副歌”。他的诉求是寻求发展策略，但其思维模式暴露了根本问题。他将“贡献”理解为一种投入，并期待相应的回报，这是一种交易心态而非共建心态。核心冲突在于，他将俱乐部视为一个等待外部资源注入的被动容器，而非一个通过内部成员“自强不息”来主动创造价值的能动主体。这种心态本质上是一种依赖和投机，希望通过别人的强大来解决自己的困境。他所谓的“贡献”，更像是一种姿态，一种扮演“最大贡献者”的欲望，而非真正地提升自我、赋能集体。他没有意识到，一个错误的模式，人越多，造成的失败和伤害就越大。此判断基于他将问题归因于“人少”而非“模式错”，并明确表达了对外部强者的期待。\n\n[ANSWER]\n\n你认为俱乐部的问题是“人太少”，并希望通过“贡献”和吸引“有本事的人”来解决，但这恰恰是你真正问题的体现。你并没有真正思考如何去“建设”，而是在思考如何“吸引”和“获取”。\n\n你口中的“贡献”，听起来像是无私的付出，但其背后隐藏着一种交易逻辑：我付出了，就应该有回报，这个回报就是俱乐部的成功，以及随之而来的个人机遇。你希望人多，本质上是希望增加遇到“副歌”的概率，让某个强者来带领你们走出困境。这就像一个等待被王子拯救的公主，而不是一个主动去屠龙的勇士。\n\n你把俱乐部看成了一个资源池，而你正因为池水稀少而焦虑。但问题不在于水少，而在于你们每个人都没有成为活的源头。一个依赖外部输血的组织，人再多也只是增加了更多的消耗者，最终会拖垮所有人。你所谓的“贡献”，是拔下自己仅剩的三根头发，然后抱怨我们让你变成了秃头。\n\n真正的贡献，不是牺牲，而是“自强不息”。当你自己通过努力成为那个“有本事的人”时，你带来的价值才是真实的。所以，问题不在于如何吸引别人，而在于你是否愿意停止等待，从此刻开始，专注于将自己锻造成一块真正的基石，哪怕最初只有你一个人。\n\n---\n\n[QUESTION]\n\n我们俱乐部里有些人，能力很强，如果去职场上卷，肯定能取得不小的成功，但他们选择了这里。我现在也决定不去职场卷，而是专心学一门技术。这条路需要投入大量时间，也就意味着我能给俱乐部的时间更少了。我这样做到底对不对？这算不算一种正确的选择？\n\n[THINK]\n\n来访者在寻求对其“学技术而非混职场”这一选择的确认，并担忧这会减少对俱乐部的投入。他将“职场”与“俱乐部”视为两个对立的空间，前者是压迫性的“大监狱”，后者则是一个理想化的“避难所”。这种二元对立的思维，暴露了他的核心误区。他将解放理解为一种“逃离”和“区隔”，即通过躲进俱乐部这个“小监狱”来对抗外面的“大监狱”。核心冲突并非时间分配，而是他对“解放路径”的根本性误解。他没有认识到，真正的解放不是逃避压迫性系统，而是深入其中，掌握足以与之抗衡的“武器”（即技术和能力），最终实现超越。俱乐部不应是一个与世隔绝的拥抱取暖之地，而应是“狱友”们交流越狱工具和策略的“工坊”。他专注于学技术，行动上是正确的，但思想上却充满矛盾，因为他仍将这一行动视为对俱乐部的背离，而非对其终极目标的贡献。此分析的前提是，他确实将俱乐部视为一个逃避现实压力的替代空间。\n\n[ANSWER]\n\n你问你的选择是否正确，这个问题本身就偏离了靶心。你真正的困惑，并非在于“学技术”与“参与俱乐部”之间的时间冲突，而在于你对“反抗”与“逃避”的混淆。\n\n你把职场看作一个必须逃离的“大监狱”，同时又把俱乐部想象成一个可以获得喘息的“小监狱”。你认为选择后者，就是一种反抗。但这是一种错觉。在监狱里，几个狱友抱在一起哭泣，并不能让他们获得自由。自由，来自于掌握越狱的工具和方法。\n\n你现在选择去“学技术”，这个行为本身是正确的，就像一个狱友开始偷偷磨一把勺子。但你的思想还停留在旧的框架里，你觉得磨勺子占用了你和狱友们一起唱歌的时间，因此感到矛盾。你没有意识到，磨好这把勺子，才是对所有狱友最根本的贡献。\n\n俱乐部不应该是一个让你逃避现实、感受温暖的舒适区，它应该是一个打气、敦促、甚至逼迫你去成为强者的训练场。当你带着从外部世界“偷来”的技术和能力回来时，你才真正为这个集体带来了希望。所以，你现在要做的，不是在两者之间选择，而是要带着“为所有狱友越狱”的目的去学习，把你的个人成长，看作是集体解放事业的一部分。"
    }
  ]
}